eiseg/__init__.py
eiseg/__main__.py
eiseg/app.py
eiseg/controller.py
eiseg/exe.py
eiseg/models.py
eiseg/run.py
eiseg/ui.py
eiseg/config/colormap.txt
eiseg/config/config.yaml
eiseg/config/labelcorres.json
eiseg/config/setting.txt
eiseg/inference/__init__.py
eiseg/inference/clicker.py
eiseg/inference/predictor/__init__.py
eiseg/inference/predictor/base.py
eiseg/inference/predictor/ops.py
eiseg/inference/transforms/__init__.py
eiseg/inference/transforms/base.py
eiseg/inference/transforms/crops.py
eiseg/inference/transforms/flip.py
eiseg/inference/transforms/limit_longest_side.py
eiseg/inference/transforms/zoom_in.py
eiseg/plugin/__init__.py
eiseg/plugin/det/__init__.py
eiseg/plugin/det/detection_model.py
eiseg/plugin/det/detinfer.py
eiseg/plugin/medical/__init__.py
eiseg/plugin/medical/med.py
eiseg/plugin/n2grid/__init__.py
eiseg/plugin/n2grid/grid.py
eiseg/plugin/n2grid/rs_grid.py
eiseg/plugin/remotesensing/__init__.py
eiseg/plugin/remotesensing/imgtools.py
eiseg/plugin/remotesensing/raster.py
eiseg/plugin/remotesensing/shape.py
eiseg/plugin/video/__init__.py
eiseg/plugin/video/inference_core.py
eiseg/plugin/video/load_model.py
eiseg/plugin/video/video_tools.py
eiseg/plugin/video/util/__init__.py
eiseg/plugin/video/util/range_transform.py
eiseg/plugin/video/util/tensor_util.py
eiseg/resource/3D.png
eiseg/resource/About.png
eiseg/resource/AutoSave.png
eiseg/resource/ChangeOutputDir.png
eiseg/resource/Clear.png
eiseg/resource/ClearLabel.png
eiseg/resource/ClearRecent.png
eiseg/resource/Close.png
eiseg/resource/Data.png
eiseg/resource/DeleteAllPolygon.png
eiseg/resource/DeletePolygon.png
eiseg/resource/DetSetting.png
eiseg/resource/Detection.png
eiseg/resource/DrawRect.png
eiseg/resource/Egypt.png
eiseg/resource/English.png
eiseg/resource/ExportLabel.png
eiseg/resource/File.png
eiseg/resource/Find.png
eiseg/resource/ImportLabel.png
eiseg/resource/Label.png
eiseg/resource/Language.png
eiseg/resource/Log.png
eiseg/resource/MedicalImaging.png
eiseg/resource/Model.png
EISeg-1.1.1.dist-info/LICENSE
EISeg-1.1.1.dist-info/METADATA
EISeg-1.1.1.dist-info/WHEEL
EISeg-1.1.1.dist-info/entry_points.txt
EISeg-1.1.1.dist-info/top_level.txt
EISeg-1.1.1.dist-info/RECORD
