Metadata-Version: 2.1
Name: EISeg
Version: 1.1.1
Summary: 交互式标注软件
Home-page: https://github.com/PaddlePaddle/PaddleSeg
Author: PaddleSeg & PaddleCV-SIG
Author-email: haoyuying@baidu.com
License: Apache Software License
Platform: UNKNOWN
Classifier: License :: OSI Approved :: Apache Software License
Classifier: Programming Language :: Python :: 3
Classifier: Programming Language :: Python :: 3.8
License-File: LICENSE
Requires-Dist: pyqt5
Requires-Dist: qtpy
Requires-Dist: opencv-python
Requires-Dist: scipy
Requires-Dist: paddleseg
Requires-Dist: albumentations
Requires-Dist: cython
Requires-Dist: pyyaml
Requires-Dist: wget
Requires-Dist: requests
Requires-Dist: easydict
Requires-Dist: scikit-image
Requires-Dist: protobuf (==3.20.0)
